crx_unpack/VERSION
crx_unpack/__init__.py
crx_unpack/__main__.py
crx_unpack/clr.py
crx_unpack/encrypted_dir.py
crx_unpack-0.1.4.data/scripts/unpack
crx_unpack-0.1.4.dist-info/DESCRIPTION.rst
crx_unpack-0.1.4.dist-info/METADATA
crx_unpack-0.1.4.dist-info/RECORD
crx_unpack-0.1.4.dist-info/WHEEL
crx_unpack-0.1.4.dist-info/metadata.json
crx_unpack-0.1.4.dist-info/top_level.txt
