Metadata-Version: 2.0
Name: crx-unpack
Version: 0.1.4
Summary: Unpack .crx files the way Chrome does
Home-page: http://crx-unpack.readthedocs.io/
Author: Mike Mabey
Author-email: mmabey@ieee.org
License: MIT
Download-URL: https://bitbucket.org/mmabey/crx_unpack/get/0.1.4.tar.gz
Keywords: crx,unpack,Chrome,Chrome OS,extension,package
Platform: UNKNOWN
Classifier: License :: OSI Approved :: MIT License
Classifier: Development Status :: 3 - Alpha
Classifier: Intended Audience :: Developers
Classifier: Topic :: Internet :: WWW/HTTP :: Browsers
Classifier: Topic :: System :: Archiving :: Compression
Classifier: Topic :: Multimedia :: Graphics :: Graphics Conversion
Classifier: Operating System :: POSIX
Classifier: Operating System :: POSIX :: Linux
Classifier: Operating System :: Microsoft :: Windows
Classifier: Operating System :: MacOS
Classifier: Programming Language :: Python :: 3
Classifier: Programming Language :: Python :: 3.5
Classifier: Programming Language :: Python :: 3.6
Requires-Dist: Pillow
Requires-Dist: colorama
Requires-Dist: docopt
